{
  "id": "s01",
  "title": "Уходы профессиональной косметикой",
  "description": "Уходы профессиональной косметикой - комплексный уход индивидуально подобранной уходовой профессиональной косметикой",
  "keywords": "комплексный уход индивидуально подобранной уходовой профессиональной косметикой",
  "url": "https://vipclinicspb.ru/service?id=s01",
  "content": {
    "name": "Уходы профессиональной косметикой",
    "preName": "Уходы профессиональной косметикой",
    "noneLast": true,
    "stats": [
      {
        "title": "Продолжительность",
        "value": "30-60 мин",
        "imgUrl": "/images/icons/time.svg"
      },
      {
        "title": "Анестезия",
        "value": "Не требуется",
        "imgUrl": "/images/icons/syringe.svg"
      },
      {
        "title": "Периодичность",
        "value": "1 раз в 7-14 дней, либо как процедура «на выход»",
        "imgUrl": "/images/icons/calendar.svg"
      },
      {
        "title": "Эффект",
        "value": "Гладкая, увлажнённая, сияющая и ухоженная кожа",
        "imgUrl": "/images/icons/stars.svg"
      },
      {
        "title": "Рекомендуемый курс",
        "value": "Рекомендуется проводить уходовые процедуры на постоянной основе",
        "imgUrl": "/images/icons/course.svg"
      },
      {
        "title": "Косметика",
        "value": "SkinCeuticals, DMK, Algomask, Holy Land, GiGi, Obagi, UltraCeuticals, Mesaltera, Mediderma, Eclado",
        "imgUrl": "/images/icons/drops.svg"
      }
    ],
    "textPlace": [
      {
        "type": "text",
        "text": "После консультации косметолога, когда вы уже узнали <span>свой тип и состояние кожи</span>, приобрели косметику для домашнего ухода, можно начать с профессионального ухода за лицом в нашей клинике, чтобы в кратчайшие сроки улучшить и преобразить кожу."
      },
      {
        "type": "text",
        "text": "Наши высококлассные специалисты ежедневно помогают своими советами и процедурам пациентам привыкнуть к мысли, что красота – это прекрасный дар природы, который стоит тщательно беречь и регулярно поддерживать. Все уходовые процедуры направленны на решение различных проблем (гиперпигментация, дегидратация, состояние кожи после инсоляции, тусклый цвет лица, постакне, акне, отечность лица, нечеткий овал, гиперкератоз и др.) и дальнейшее регулярное <span>поддержание полученного результата</span>."
      },
      {
        "type": "text",
        "text": "С помощью грамотно подобранной процедуры специалист уже за 1 процедуру преобразит вашу кожу, придаст ей здоровое сияние, а после курса процедур значительно повысится тонус кожи и ваша самооценка."
      },
      {
        "type": "text",
        "text": "Продолжительность уходовых процедур <span>30-75 мин</span>, кроме этого вы не испытываете никаких болезненных или неприятных ощущений, а просто отдыхаете и расслабляетесь."
      },
      {
        "type": "text",
        "text": "Многие из уходовых процедур разрешено проводить даже в период беременности и лактации, всегда уточняйте подобную информацию у своего специалиста."
      }
    ],
    "pricePlace": {
      "type": "only",
      "value": [
        {
          "title": "Максимальное увлажнение «Standart»",
          "description": "Очищение/тонизация/энзимный пилинг/активная сыворотка/альгинатная маска «Algomask»/завершающий крем",
          "prices": [{ "time": "30 мин", "volume": "", "price": "3800₽" }]
        },
        {
          "title": "Максимальное увлажнение «Premium»",
          "description": "Очищение/тонизация/миндальный пилинг/экспресс-массаж лица (10 мин)/ активная сыворотка/альгинатная маска «Algomask»/завершающий крем",
          "prices": [{ "time": "45 мин", "volume": "", "price": "4200₽" }]
        },
        {
          "title": "Максимальное увлажнение «Deluxe»",
          "description": "Очищение/тонизация/пилинг на выбор доктора /массаж лица (20 мин)/активная сыворотка/ двухфазная альгинатная маска «Casmara»/завершающий крем",
          "prices": [{ "time": "40 мин", "volume": "", "price": "4400₽" }]
        },
        {
          "title": "Профессиональный уход «Esthe-filler»",
          "description": "(Institut Esthederm, Франция)",
          "prices": [{ "time": "60 мин", "volume": "", "price": "6600₽" }]
        },
        {
          "title": "«Мать невесты» (DMK)",
          "description": "лицо/шея/декольте",
          "prices": [{ "time": "75 мин", "volume": "", "price": "6800₽" }]
        },
        {
          "title": "«Голливудский лифтинг» (DMK)",
          "description": "лицо/шея/декольте",
          "prices": [{ "time": "60 мин", "volume": "", "price": "6400₽" }]
        },
        {
          "title": "«Перезагрузка кожи» Hydropeptide (США)",
          "description": "",
          "prices": [{ "time": "75 мин", "volume": "", "price": "6700₽" }]
        },
        {
          "title": "Процедура на выход «Огонь и лёд» на косметике «ISCLINICAL» (США)",
          "description": "",
          "prices": [{ "time": "60 мин", "volume": "", "price": "6800₽" }]
        },
        {
          "title": "«Импульс молодости» Hydropeptide (США)",
          "description": "",
          "prices": [{ "time": "75 мин", "volume": "", "price": "6200₽" }]
        },
        {
          "title": "«Smart-увлажнение» Hydropeptide (США)",
          "description": "",
          "prices": [{ "time": "60 мин", "volume": "", "price": "6400₽" }]
        }
      ]
    }
  },
  "images": {
    "desktop": {
      "first": "/images/services/s01/1.png",
      "second": "/images/services/s01/2.png",
      "third": "/images/services/s01/3.png"
    },
    "mobile": {
      "first": "/images/services/s01/1.1.png",
      "second": "/images/services/s01/2.1.png"
    }
  }
}
